githubutilsapi/__init__.py
githubutilsapi/exceptions/__init__.py
githubutilsapi/interface/__init__.py
github_utils_api-0.69.0.dist-info/LICENSE
github_utils_api-0.69.0.dist-info/METADATA
github_utils_api-0.69.0.dist-info/WHEEL
github_utils_api-0.69.0.dist-info/top_level.txt
github_utils_api-0.69.0.dist-info/RECORD
