Metadata-Version: 2.1
Name: github-utils-api
Version: 0.69.0
Summary: Small library to cover non provided methods by pygithub
Author: Pablo Toledo
Classifier: Programming Language :: Python :: 3
Classifier: License :: OSI Approved :: MIT License
Classifier: Operating System :: OS Independent
Requires-Python: >=3.6
License-File: LICENSE
Requires-Dist: requests
